<annotation>
	<folder>images</folder>
	<filename>food_49.jpg</filename>
	<path>H:\food_waste\data\images\food_49.jpg</path>
	<source>
		<database>Unknown</database>
	</source>
	<size>
		<width>1279</width>
		<height>1706</height>
		<depth>3</depth>
	</size>
	<segmented>0</segmented>
	<object>
		<name>plate</name>
		<pose>Unspecified</pose>
		<truncated>0</truncated>
		<difficult>0</difficult>
		<bndbox>
			<xmin>62</xmin>
			<ymin>629</ymin>
			<xmax>1216</xmax>
			<ymax>1541</ymax>
		</bndbox>
	</object>
	<object>
		<name>mild</name>
		<pose>Unspecified</pose>
		<truncated>0</truncated>
		<difficult>0</difficult>
		<bndbox>
			<xmin>326</xmin>
			<ymin>639</ymin>
			<xmax>870</xmax>
			<ymax>985</ymax>
		</bndbox>
	</object>
</annotation>
