<annotation>
	<folder>images</folder>
	<filename>food_105.jpg</filename>
	<path>H:\food_waste\data\images\food_105.jpg</path>
	<source>
		<database>Unknown</database>
	</source>
	<size>
		<width>1279</width>
		<height>1706</height>
		<depth>3</depth>
	</size>
	<segmented>0</segmented>
	<object>
		<name>plate</name>
		<pose>Unspecified</pose>
		<truncated>0</truncated>
		<difficult>0</difficult>
		<bndbox>
			<xmin>372</xmin>
			<ymin>529</ymin>
			<xmax>1100</xmax>
			<ymax>1647</ymax>
		</bndbox>
	</object>
	<object>
		<name>mild</name>
		<pose>Unspecified</pose>
		<truncated>0</truncated>
		<difficult>0</difficult>
		<bndbox>
			<xmin>446</xmin>
			<ymin>713</ymin>
			<xmax>934</xmax>
			<ymax>1188</ymax>
		</bndbox>
	</object>
	<object>
		<name>tissue</name>
		<pose>Unspecified</pose>
		<truncated>1</truncated>
		<difficult>0</difficult>
		<bndbox>
			<xmin>554</xmin>
			<ymin>908</ymin>
			<xmax>1193</xmax>
			<ymax>1706</ymax>
		</bndbox>
	</object>
</annotation>
